alpacka/Pipeline.py
alpacka/__init__.py
alpacka/functions/__init__.py
alpacka/functions/presentation_functions.py
alpacka/functions/statistic_methods.py
alpacka/pipes/__init__.py
alpacka/pipes/lrp_pipe.py
alpacka/pipes/ncof_pipeline.py
alpacka/pipes/tfidf_pipeline.py
alpacka-0.1.2.dist-info/LICENCE
alpacka-0.1.2.dist-info/METADATA
alpacka-0.1.2.dist-info/WHEEL
alpacka-0.1.2.dist-info/top_level.txt
alpacka-0.1.2.dist-info/RECORD
