Metadata-Version: 2.1
Name: alpacka
Version: 0.1.2
Summary: The alpacka Python package, used to extract and visualize metadata from text data sets
Home-page: https://github.com/BernhardMoller/alpacka
Author: Fredrik Möller
Author-email: fredrikmoller@recordefuture.com
License: LICENCE.txt
Platform: UNKNOWN
Classifier: Programming Language :: Python :: 3
Classifier: License :: OSI Approved :: MIT License
Classifier: Operating System :: OS Independent
Requires-Python: >=3.6
Requires-Dist: keras (>=2.4.3)
Requires-Dist: scikit-learn (>=0.24.2)
Requires-Dist: matplotlib (>=3.3.4)
Requires-Dist: tensorflow (>=2.2)
Requires-Dist: numpy (>=1.18)
